build/lib/opossum/__init__.py
build/lib/opossum/dml.py
build/lib/opossum/dml_plot.py
build/lib/opossum/helpers.py
build/lib/opossum/main.py
build/lib/opossum/opossum.py
build/lib/opossum/plot_creation.py
build/lib/opossum/plot_functions.py
double_machine_learning_example/dml.py
double_machine_learning_example/dml_plot.py
opossum/__init__.py
opossum/dml.py
opossum/dml_plot.py
opossum/helpers.py
opossum/main.py
opossum/opossum.py
opossum/plot_creation.py
opossum/plot_functions.py
opossum-0.2.1.dist-info/LICENSE
opossum-0.2.1.dist-info/METADATA
opossum-0.2.1.dist-info/WHEEL
opossum-0.2.1.dist-info/top_level.txt
opossum-0.2.1.dist-info/RECORD
