Metadata-Version: 2.1
Name: opossum
Version: 0.2.1
Summary: Simulated Data Generating Process
Home-page: https://github.com/jgitr/opossum
Author: Tobias Krebs, Julian Winkel
Author-email: julian.winkel@hu-berlin.de
License: MIT
Platform: UNKNOWN
Requires-Dist: numpy
Requires-Dist: statsmodels
Requires-Dist: seaborn
Requires-Dist: matplotlib
Requires-Dist: scipy
